{
  "date": "2026-02-23",
  "period": "evening",
  "content": "📊 市场简报 | 02.23 17:00\n\n🔍 今日核心观察：市场在极端恐惧与宏观冲击下，衍生品空头拥挤，但期权市场押注反弹，鲸鱼行为出现背离信号。\n\n市场正经历一场典型的“宏观冲击后的情绪冰点”。The Block的报道直接点出“宏观冲击震撼了脆弱的市场”，结合黎巴嫩考虑出售黄金储备等新闻，全球避险情绪浓厚。然而，在价格普跌、情绪指标一片哀嚎的表象下，衍生品和链上数据揭示了几个关键的背离与潜在转折点。\n\n🌡️ 情绪与结构的深度背离\n恐惧贪婪指数连续一周维持在个位数的“极端恐惧”区间，今日更是低至5。这通常是逆向指标，但需要结合其他数据判断。\n↳ 关键背离在于：情绪极度悲观，但市场并未出现大规模结构性崩坏。总TVL日增+3.21%，稳定币总市值微涨，USDT、USDC仍在净流入。这说明底层流动性并未恐慌性抽离，下跌更多由现货抛售和杠杆清算驱动。\n↳ 另一个背离是价格下跌 vs. 期权持仓增加。BTC/ETH期权总OI在24h内分别增加2.1%和1.9%，尤其是在价格下跌时，这表明有资金在逢低布局期权头寸，而非单纯离场。\n\n💥 爆仓结构与资金费率的空头陷阱信号\n今日的爆仓数据是教科书级别的“多头踩踏”：\n- 全市场24h爆仓$486.5M，其中多头占比高达89.5%。\n- BTC、ETH、SOL的多头爆仓占比均超过90%，HYPE更是达到惊人的99%。\n这解释了为何价格下跌如此顺畅——杠杆多头被集中清剿。\n\n然而，资金费率揭示了另一面：\n- BTC、ETH、SOL的永续合约资金费率全数为负（均值分别为-0.0057%、-0.0192%、-0.0387%）。\n- 特别是SOL，在Binance和MEXC的费率低至-0.0535%，空头持仓需持续付费给多头。\n↳ 这是一个强烈的矛盾信号：市场一边倒地爆仓多头（结果），但资金费率显示空头头寸已经过于拥挤（原因）。这种结构往往预示着，一旦抛压减弱，空头平仓（或被迫转为付费方）可能引发快速反弹。Hyperliquid上SOL高达-5.3%的年化负费率，更是将这种拥挤推向了极端。\n\n🪙 鲸鱼行为：恐慌中的“贪婪”暗流\n链上快讯显示了与市场情绪相反的“聪明钱”行为：\n1.  巨鲸抄底ETH：早期布道者Erik Voorhees斥资2038万美元买入9911枚ETH。这是公开的、大规模的现货买入，表达了对当前ETH价格的强烈价值认同。\n2.  交易员激进做多BTC：某交易员通过循环借贷加仓61.93枚WBTC（价值409万美元），尽管风险较高（健康度1.72），但这是一种坚定的杠杆看多行为。\n3.  交易所提币：新建钱包从Bitfinex提取500枚BTC（约3281万美元）。在下跌中从交易所提走大额BTC，通常不是出于抛售目的，而是转为托管或准备长期持有。\n↳ 这些行为与散户的“极端恐惧”和市场的“宏观冲击”叙事形成鲜明对比，构成了值得关注的“鲸鱼-散户情绪背离”。\n\n📊 期权市场：MaxPain揭示短期博弈焦点\n期权数据提供了精准的战场地图：\n- BTC短期（2月24日到期）MaxPain在$66,500，且Put/Call Ratio为1.21（看跌期权价值更高），这意味着期权卖方有动力将价格压制在$66,500以下以获取最大利润。这正好解释了当前价格在$66,000附近的挣扎。\n- 但中期（2月25、26日到期）的P/C Ratio迅速降至0.53和0.46，看涨期权占优，MaxPain也上移至$67,000。这表明市场预期短期压制后，下周初有反弹需求。\n- ETH期权结构更偏空：2月25、26日到期的P/C Ratio高达1.69和2.36，MaxPain在$1850-$1925，显示短期内ETH面临的期权抛压比BTC更大，这与ETH资金费率更负、跌幅更深相吻合。\n\n⚠️ 值得警惕的风险点\n1.  HYPE的异常波动：作为Hyperliquid平台币，HYPE登上跌幅榜（-6.5%），且24h爆仓中多头占比99%。这可能是平台内高杠杆交易导致的局部崩盘，需警惕其风险外溢至整个生态。\n2.  Coinbase持续负溢价：已连续39日，表明美国机构/大资金在现货市场的购买意愿持续疲软，这与鲸鱼链上买入形成区域背离，需观察哪一方力量最终胜出。\n3.  清算墙威胁：Coinglass数据显示，若BTC突破$68,000，将有$9.66亿空单面临清算，这既是上行催化剂，也意味着上方阻力巨大。反之，跌破$64,000会引发更多多单清算。\n\n💎 总结\n综合判断：市场处于“宏观情绪冲击”与“衍生品技术性反弹需求”的对抗阶段。极度恐惧的情绪、一边倒的多头爆仓和持续的负溢价描绘了眼前的悲观图景。然而，极端的负资金费率（空头拥挤）、鲸鱼的现货抄底行为以及期权市场对中期反弹的押注，构成了潜在的反弹火种。\n关键价位：\n- BTC：短期受$66,500（MaxPain）压制，下方关键支撑$64,000（多空清算分界线）。有效突破$66,500并站稳，可能触发空头平仓，向上测试$68,000的巨量清算墙。\n- ETH：面临更大期权抛压，关注$1,925和$1,850两个MaxPain点位的争夺。\n核心风险点：1）宏观面再出利空，击穿$64,000引发新一轮多杀多；2）HYPE等局部风险意外扩散；3）Coinbase负溢价持续，表明主力资金仍在观望，反弹可能缺乏持续买盘。当前市场不宜盲目追空，重点观察$64,000-$66,500区间的突破方向。",
  "html": "📊 市场简报 | 02.23 17:00\n\n🔍 <b>今日核心观察：市场在极端恐惧与宏观冲击下，衍生品空头拥挤，但期权市场押注反弹，鲸鱼行为出现背离信号。</b>\n\n市场正经历一场典型的“宏观冲击后的情绪冰点”。<a href=\"https://www.theblock.co/post/390747/bitcoin-sinks-below-65000?utm_source=rss&utm_medium=rss\">The Block的报道</a>直接点出“宏观冲击震撼了脆弱的市场”，结合黎巴嫩考虑出售黄金储备等新闻，全球避险情绪浓厚。然而，在价格普跌、情绪指标一片哀嚎的表象下，衍生品和链上数据揭示了几个关键的背离与潜在转折点。\n\n🌡️ <b>情绪与结构的深度背离</b>\n恐惧贪婪指数连续一周维持在个位数的“极端恐惧”区间，今日更是低至5。这通常是逆向指标，但需要结合其他数据判断。\n↳ 关键背离在于：<b>情绪极度悲观，但市场并未出现大规模结构性崩坏。</b>总TVL日增+3.21%，稳定币总市值微涨，USDT、USDC仍在净流入。这说明底层流动性并未恐慌性抽离，下跌更多由现货抛售和杠杆清算驱动。\n↳ 另一个背离是<b>价格下跌 vs. 期权持仓增加</b>。BTC/ETH期权总OI在24h内分别增加2.1%和1.9%，尤其是在价格下跌时，这表明有资金在逢低布局期权头寸，而非单纯离场。\n\n💥 <b>爆仓结构与资金费率的空头陷阱信号</b>\n今日的爆仓数据是教科书级别的“多头踩踏”：\n- 全市场24h爆仓$486.5M，其中<b>多头占比高达89.5%</b>。\n- BTC、ETH、SOL的多头爆仓占比均超过90%，HYPE更是达到惊人的99%。\n这解释了为何价格下跌如此顺畅——杠杆多头被集中清剿。\n\n然而，资金费率揭示了另一面：\n- <b>BTC、ETH、SOL的永续合约资金费率全数为负</b>（均值分别为-0.0057%、-0.0192%、-0.0387%）。\n- 特别是SOL，在Binance和MEXC的费率低至-0.0535%，<b>空头持仓需持续付费给多头</b>。\n↳ 这是一个强烈的矛盾信号：市场一边倒地爆仓多头（结果），但资金费率显示空头头寸已经过于拥挤（原因）。这种结构往往预示着，一旦抛压减弱，空头平仓（或被迫转为付费方）可能引发快速反弹。Hyperliquid上SOL高达-5.3%的年化负费率，更是将这种拥挤推向了极端。\n\n🪙 <b>鲸鱼行为：恐慌中的“贪婪”暗流</b>\n链上快讯显示了与市场情绪相反的“聪明钱”行为：\n1.  <b>巨鲸抄底ETH</b>：早期布道者Erik Voorhees斥资2038万美元买入9911枚ETH。这是公开的、大规模的现货买入，表达了对当前ETH价格的强烈价值认同。\n2.  <b>交易员激进做多BTC</b>：某交易员通过循环借贷加仓61.93枚WBTC（价值409万美元），尽管风险较高（健康度1.72），但这是一种坚定的杠杆看多行为。\n3.  <b>交易所提币</b>：新建钱包从Bitfinex提取500枚BTC（约3281万美元）。在下跌中从交易所提走大额BTC，通常不是出于抛售目的，而是转为托管或准备长期持有。\n↳ 这些行为与散户的“极端恐惧”和市场的“宏观冲击”叙事形成鲜明对比，构成了值得关注的<b>“鲸鱼-散户情绪背离”</b>。\n\n📊 <b>期权市场：MaxPain揭示短期博弈焦点</b>\n期权数据提供了精准的战场地图：\n- <b>BTC短期（2月24日到期）MaxPain在$66,500</b>，且Put/Call Ratio为1.21（看跌期权价值更高），这意味着期权卖方有动力将价格压制在$66,500以下以获取最大利润。这正好解释了当前价格在$66,000附近的挣扎。\n- 但<b>中期（2月25、26日到期）的P/C Ratio迅速降至0.53和0.46</b>，看涨期权占优，MaxPain也上移至$67,000。这表明市场预期短期压制后，下周初有反弹需求。\n- <b>ETH期权结构更偏空</b>：2月25、26日到期的P/C Ratio高达1.69和2.36，MaxPain在$1850-$1925，显示短期内ETH面临的期权抛压比BTC更大，这与ETH资金费率更负、跌幅更深相吻合。\n\n⚠️ <b>值得警惕的风险点</b>\n1.  <b>HYPE的异常波动</b>：作为Hyperliquid平台币，HYPE登上跌幅榜（-6.5%），且24h爆仓中多头占比99%。这可能是平台内高杠杆交易导致的局部崩盘，需警惕其风险外溢至整个生态。\n2.  <b>Coinbase持续负溢价</b>：已连续39日，表明美国机构/大资金在现货市场的购买意愿持续疲软，这与鲸鱼链上买入形成区域背离，需观察哪一方力量最终胜出。\n3.  <b>清算墙威胁</b>：Coinglass数据显示，若BTC突破$68,000，将有$9.66亿空单面临清算，这既是上行催化剂，也意味着上方阻力巨大。反之，跌破$64,000会引发更多多单清算。\n\n💎 <b>总结</b>\n<b>综合判断</b>：市场处于“宏观情绪冲击”与“衍生品技术性反弹需求”的对抗阶段。极度恐惧的情绪、一边倒的多头爆仓和持续的负溢价描绘了眼前的悲观图景。然而，极端的负资金费率（空头拥挤）、鲸鱼的现货抄底行为以及期权市场对中期反弹的押注，构成了潜在的反弹火种。\n<b>关键价位</b>：\n- <b>BTC</b>：短期受$66,500（MaxPain）压制，下方关键支撑$64,000（多空清算分界线）。有效突破$66,500并站稳，可能触发空头平仓，向上测试$68,000的巨量清算墙。\n- <b>ETH</b>：面临更大期权抛压，关注$1,925和$1,850两个MaxPain点位的争夺。\n<b>核心风险点</b>：1）宏观面再出利空，击穿$64,000引发新一轮多杀多；2）HYPE等局部风险意外扩散；3）Coinbase负溢价持续，表明主力资金仍在观望，反弹可能缺乏持续买盘。当前市场不宜盲目追空，重点观察$64,000-$66,500区间的突破方向。",
  "generated_at": "2026-02-23T17:00:50.116022"
}